graphene_sentry/__init__.py
graphene_sentry/views.py
graphene_sentry-0.4.0.dist-info/AUTHORS.md
graphene_sentry-0.4.0.dist-info/LICENSE
graphene_sentry-0.4.0.dist-info/METADATA
graphene_sentry-0.4.0.dist-info/WHEEL
graphene_sentry-0.4.0.dist-info/top_level.txt
graphene_sentry-0.4.0.dist-info/RECORD
