Metadata-Version: 2.1
Name: graphene-sentry
Version: 0.4.0
Summary: Capture Sentry exceptions in Graphene views
Home-page: https://github.com/Alegzander/graphene-sentry
Author: Alexander Lushnikov
Author-email: alexander.aka.alegz@gmail.com
License: MIT license
Keywords: GraphQL graphene sentry
Platform: UNKNOWN
Classifier: Development Status :: 4 - Beta
Classifier: Intended Audience :: Developers
Classifier: License :: OSI Approved :: MIT License
Classifier: Natural Language :: English
Classifier: Programming Language :: Python :: 3.6
Classifier: Programming Language :: Python :: 3.7
Requires-Dist: graphene-django (>=2.2.0<=2.4.0)
Requires-Dist: graphene-file-upload (==1.2.2)
Requires-Dist: sentry-sdk (>=0.5.2<=0.10.1)
